mnemosyne_journal/.DS_Store
mnemosyne_journal/__init__.py
mnemosyne_journal/cli.py
mnemosyne_journal/gui_qt.py
mnemosyne_journal/gui_tkinter.py
mnemosyne_journal/journal.py
mnemosyne_journal-3.0.1.dist-info/WHEEL
mnemosyne_journal-3.0.1.dist-info/entry_points.txt
mnemosyne_journal-3.0.1.dist-info/METADATA
mnemosyne_journal-3.0.1.dist-info/RECORD
