Metadata-Version: 2.4
Name: mnemosyne-journal
Version: 3.0.1
Summary: A simple encrypted journaling application that is named after the ancient Greek goddess of memories.
Keywords: journaling
Author: siru
Author-email: siru <siru@codessh.de>
License-Expression: GPL-3.0-or-later
Classifier: Development Status :: 1 - Planning
Classifier: License :: OSI Approved :: GNU General Public License v3 or later (GPLv3+)
Classifier: Natural Language :: English
Classifier: Programming Language :: Python :: 3
Classifier: Topic :: Office/Business :: News/Diary
Classifier: Typing :: Typed
Requires-Dist: argon2-cffi>=25.1.0
Requires-Dist: darkdetect>=0.8.0
Requires-Dist: pycryptodomex>=3.23.0
Requires-Dist: sv-ttk>=2.6.1
Maintainer: siru
Maintainer-email: siru <siru@codessh.de>
Requires-Python: >=3.13
Project-URL: documentation, https://codeberg.org/siru/mnemosyne-journal/wiki
Project-URL: homepage, https://mnemosyne.codessh.de/
Project-URL: issues, https://codeberg.org/siru/mnemosyne-journal/issues
Project-URL: source, https://codeberg.org/siru/mnemosyne-journal
